LICENSE
MANIFEST.in
README
kindlereader.py
setup.py
kindlereader.egg-info/PKG-INFO
kindlereader.egg-info/SOURCES.txt
kindlereader.egg-info/dependency_links.txt
kindlereader.egg-info/requires.txt
kindlereader.egg-info/top_level.txt
krlib/ImageDownloader.py
krlib/KVData.py
krlib/Reader.py
krlib/Tools.py
krlib/__init__.py
krlib/configtemplate.py
krlib/kindletemplate.py