Metadata-Version: 1.1
Name: kindlereader
Version: 0.0.2
Summary: generate news for kindle reader from rss
Home-page: https://github.com/fireinice/kindlereader2
Author: Zigler Zhang<zigler.zhang@gmail.com>
Author-email: zigler.zhang@gmail.com
License: The MIT License (MIT)
